pythologist_test_images/__init__.py
pythologisttestimages/__init__.py
pythologist_test_images-1.0.0.dist-info/LICENSE
pythologist_test_images-1.0.0.dist-info/METADATA
pythologist_test_images-1.0.0.dist-info/WHEEL
pythologist_test_images-1.0.0.dist-info/top_level.txt
pythologist_test_images-1.0.0.dist-info/RECORD
