Metadata-Version: 2.1
Name: pythologist-test-images
Version: 1.0.0
Summary: Real and simulated data for testing image analysis software
Home-page: https://github.com/jason-weirather/pythologist-test-images
Author: Jason L Weirather
Author-email: jason.weirather@gmail.com
License: Apache License, Version 2.0
Keywords: bioinformatics
Platform: UNKNOWN
Classifier: Development Status :: 3 - Alpha
Classifier: Intended Audience :: Science/Research
Classifier: Topic :: Scientific/Engineering :: Bio-Informatics
Classifier: License :: OSI Approved :: Apache Software License
Provides-Extra: h5
Requires-Dist: pythologistreader ; extra == 'h5'
Requires-Dist: pythologist ; extra == 'h5'
